{
  "hero_badge": "框架无关的验证码库",
  "hero_title": "Better Captcha",
  "hero_description": "无需更改代码即可切换验证码提供商。支持 React、Solid、Vue、Svelte、Qwik 和 Lit。",
  "hero_button_started": "快速开始",
  "hero_button_github": "GitHub",
  "stats_npm_downloads": "npm 周下载量",
  "stats_github_stars": "GitHub 星标",
  "stats_captcha_providers": "验证码提供商",
  "stats_frameworks": "框架",
  "frameworks_title": "支持的框架",
  "frameworks_description": "选择你喜欢的框架。相同的 API，相同的功能，零妥协。",
  "framework_react": "React",
  "framework_solid": "Solid",
  "framework_vue": "Vue",
  "framework_svelte": "Svelte",
  "framework_qwik": "Qwik",
  "framework_lit": "Lit",
  "features_title": "功能特性",
  "features_description": "无缝集成验证码到你的应用所需的一切",
  "feature_unified_api_title": "统一 API",
  "feature_unified_api_description": "所有验证码提供商使用一致的接口。无需更改代码即可切换提供商。",
  "feature_smart_loading_title": "智能加载",
  "feature_smart_loading_description": "仅在需要时加载供应商脚本。更好的性能和更小的包体积。",
  "feature_auto_theme_title": "自动主题",
  "feature_auto_theme_description": "自动适应应用的主题，即使提供商原生不支持。",
  "feature_type_safe_title": "类型安全",
  "feature_type_safe_description": "完整的 TypeScript 支持，零额外依赖。轻量且快速。",
  "feature_programmatic_control_title": "编程控制",
  "feature_programmatic_control_description": "通过简单的 handle API 以编程方式执行、重置和管理验证码组件。",
  "feature_framework_agnostic_title": "框架无关",
  "feature_framework_agnostic_description": "支持 React、Solid、Vue、Svelte、Qwik 和 Lit。所有地方都有相同的功能。",
  "cta_title": "准备好开始了吗？",
  "cta_description": "选择你的框架，在几分钟内开始保护你的表单。",
  "cta_button": "查看文档"
}
